setup.py
get_time/__init__.py
sawyer_get_time.egg-info/PKG-INFO
sawyer_get_time.egg-info/SOURCES.txt
sawyer_get_time.egg-info/dependency_links.txt
sawyer_get_time.egg-info/entry_points.txt
sawyer_get_time.egg-info/top_level.txt