Metadata-Version: 1.0
Name: sawyer-get-time
Version: 1.1.0
Summary: 获取任意时间/获取当前的时间戳/时间转时间戳/时间戳转时间
Home-page: https://github.com/GBwuka
Author: sjh
Author-email: sjh.0522@163.com
License: UNKNOWN
Platform: UNKNOWN
